django_changeset/__init__.py
django_changeset/migrations/0001_initial.py
django_changeset/migrations/0002_add_index_changesettype.py
django_changeset/migrations/0003_restore_soft_delete.py
django_changeset/migrations/0004_object_references.py
django_changeset/migrations/__init__.py
django_changeset/models/__init__.py
django_changeset/models/fields.py
django_changeset/models/mixins.py
django_changeset/models/models.py
django_changeset/models/queryset.py
django_changeset-1.1.0.dist-info/LICENSE
django_changeset-1.1.0.dist-info/METADATA
django_changeset-1.1.0.dist-info/WHEEL
django_changeset-1.1.0.dist-info/top_level.txt
django_changeset-1.1.0.dist-info/RECORD
